obsidian_media/__init__.py
obsidian_media/extension.py
obsidian_media-1.0.0.dist-info/METADATA
obsidian_media-1.0.0.dist-info/WHEEL
obsidian_media-1.0.0.dist-info/entry_points.txt
obsidian_media-1.0.0.dist-info/licenses/LICENSE
obsidian_media-1.0.0.dist-info/RECORD
