Metadata-Version: 2.3
Name: obsidian-media
Version: 1.0.0
Summary: A plugin for Python-Markdown that allows you to embed media files as in Obsidian.
Project-URL: Homepage, https://github.com/GooRoo/obsidian-media
Project-URL: Issues, https://github.com/GooRoo/obsidian-media/issues
Project-URL: Repository, https://github.com/GooRoo/obsidian-media.git
License-File: LICENSE
Classifier: Development Status :: 5 - Production/Stable
Classifier: Environment :: Plugins
Classifier: License :: OSI Approved :: BSD License
Classifier: Programming Language :: Python :: 3
Classifier: Programming Language :: Python :: 3.10
Classifier: Topic :: Documentation
Classifier: Topic :: Software Development :: Documentation
Classifier: Topic :: Text Processing :: Markup :: HTML
Classifier: Topic :: Text Processing :: Markup :: Markdown
Requires-Python: >=3.10
Requires-Dist: markdown>=3.7
